{
  "Title": "出題ッ！理事長チェック！",
  "TextBlockList": [
    {
      "Name": "",
      "Text": "",
      "ChoiceDataList": [],
      "ColorTextInfoList": []
    },
    {
      "Name": "モノローグ",
      "Text": "ある日、担当ウマ娘のトレーニングを終え、\n部屋に帰ろうとしていた時――",
      "ChoiceDataList": [],
      "ColorTextInfoList": []
    },
    {
      "Name": "秋川理事長",
      "Text": "――見事ッ！",
      "ChoiceDataList": [],
      "ColorTextInfoList": []
    },
    {
      "Name": "秋川理事長",
      "Text": "いやはや、感銘ッ！\n彼女の目標を見据えた堅実なメニューを\n考案し、実行しているようだな。",
      "ChoiceDataList": [],
      "ColorTextInfoList": []
    },
    {
      "Name": "秋川理事長",
      "Text": "さらに、メニューを消化するだけでなく、\nコンディションに合わせ変更も挟んでいる――",
      "ChoiceDataList": [],
      "ColorTextInfoList": []
    },
    {
      "Name": "秋川理事長",
      "Text": "まさに天晴ッ！\n互いの信頼なくては、なかなかできんことだ！",
      "ChoiceDataList": [
        "そこまで見ていらしたとは……"
      ],
      "ColorTextInfoList": []
    },
    {
      "Name": "秋川理事長",
      "Text": "はっはっは！\u3000生徒ひとりひとりに\n目を配るのは、学園を預かる者の義務ッ！",
      "ChoiceDataList": [],
      "ColorTextInfoList": []
    },
    {
      "Name": "秋川理事長",
      "Text": "――生徒の人生を左右する、\nトレーナーたちの手腕を把握しておくのもな。",
      "ChoiceDataList": [],
      "ColorTextInfoList": []
    },
    {
      "Name": "秋川理事長",
      "Text": "はっは！\u3000堅苦しい話はここまでとして、\nこれから食事でもどうだね？\n無論、わたしの奢りっ！",
      "ChoiceDataList": [
        "えっ、いいんですか？"
      ],
      "ColorTextInfoList": []
    },
    {
      "Name": "秋川理事長",
      "Text": "うむっ！\u3000久々に少し時間が空いたのでな！\nわたしの馴染みの店に連れていってあげよう！",
      "ChoiceDataList": [],
      "ColorTextInfoList": []
    },
    {
      "Name": "モノローグ",
      "Text": "そして秋川理事長に連れてこられたのは……\n“超高級”という言葉をそのまま\n地面から生やしたような巨大ビルだった。",
      "ChoiceDataList": [],
      "ColorTextInfoList": []
    },
    {
      "Name": "秋川理事長",
      "Text": "わっはっは！\u3000ここの最上階にある寿司屋が\nわたしの行きつけでな！\u3000まさに絶品ッ！",
      "ChoiceDataList": [],
      "ColorTextInfoList": []
    },
    {
      "Name": "秋川理事長",
      "Text": "だが、入る前にっ！\n君にひとつ聞いておきたいことがある！",
      "ChoiceDataList": [],
      "ColorTextInfoList": []
    },
    {
      "Name": "秋川理事長",
      "Text": "一流のトレーナーたるもの、日常の所作\nひとつひとつにも一貫した思想が表れるもの\n――と、わたしは考えていてな。",
      "ChoiceDataList": [],
      "ColorTextInfoList": []
    },
    {
      "Name": "秋川理事長",
      "Text": "質問ッ！\u3000君は――\n寿司を食べる時、どのネタから頼むかね？",
      "ChoiceDataList": [
        "何があっても絶対カニサラダ軍艦です！",
        "淡白なネタからじっくり楽しみますね"
      ],
      "ColorTextInfoList": []
    },
    {
      "Name": "秋川理事長",
      "Text": "意外ッ！\n初手でカニサラダ軍艦ッ！？",
      "ChoiceDataList": [],
      "ColorTextInfoList": []
    },
    {
      "Name": "秋川理事長",
      "Text": "ふ～む……カニサラダといえば、\n大衆店で提供されるもの、\nというイメージを持たれがちなネタ！",
      "ChoiceDataList": [],
      "ColorTextInfoList": []
    },
    {
      "Name": "秋川理事長",
      "Text": "が、同時に――人は、どこかで思っているっ！\n超一流の職人が本気でカニサラダを作った時、\nいかなものができるのだろう……と。",
      "ChoiceDataList": [],
      "ColorTextInfoList": []
    },
    {
      "Name": "秋川理事長",
      "Text": "あえて今、君はその冒険に\n踏み切ろうというのか。…………",
      "ChoiceDataList": [],
      "ColorTextInfoList": []
    },
    {
      "Name": "秋川理事長",
      "Text": "――はっはっは！\u3000面白い！\n君とウマ娘がどのような軌跡を残していくか、\n大いに楽しみであるっ！",
      "ChoiceDataList": [],
      "ColorTextInfoList": []
    },
    {
      "Name": "モノローグ",
      "Text": "そして――摩天楼を昇っていった。\n2人で超高級カニサラダ軍艦を頼むために。",
      "ChoiceDataList": [],
      "ColorTextInfoList": []
    },
    {
      "Name": "秋川理事長",
      "Text": "ほう、なるほど。淡白な味から始め、\n徐々に濃厚なネタへ攻めていく。\nまさに王道の醍醐味ッ！",
      "ChoiceDataList": [],
      "ColorTextInfoList": []
    },
    {
      "Name": "秋川理事長",
      "Text": "そして――同時に、万全な状態の舌で、\n職人の技量を試し、味わっていく行為ッ！",
      "ChoiceDataList": [],
      "ColorTextInfoList": []
    },
    {
      "Name": "秋川理事長",
      "Text": "なるほど。君は、担当ウマ娘、\nライバルの実力を腰を据えてじっくり分析し、\n堅実に勝利を掴んでいくタイプ、と見たっ！",
      "ChoiceDataList": [],
      "ColorTextInfoList": []
    },
    {
      "Name": "秋川理事長",
      "Text": "……しかーし！\u3000それを成していくには、\nものの本質を的確に見抜くセンスが不可欠ッ！",
      "ChoiceDataList": [],
      "ColorTextInfoList": []
    },
    {
      "Name": "秋川理事長",
      "Text": "というわけで！\u3000今日は美味しい寿司を\nじっくり味わい、センスを磨くとしよう！\nわっはっは！",
      "ChoiceDataList": [],
      "ColorTextInfoList": []
    },
    {
      "Name": "モノローグ",
      "Text": "そして――時おり仕事の話もまじえつつ、\n美味しい寿司をご馳走になったのだった。",
      "ChoiceDataList": [],
      "ColorTextInfoList": []
    }
  ]
}