{
    "Title": "名指导",
    "TextBlockList": [
        {
            "Name": "",
            "Text": "",
            "ChoiceDataList": [],
            "ColorTextInfoList": []
        },
        {
            "Name": "伏特加",
            "Text": "──好耶！！\n超厉害的！创下新纪录了！！",
            "ChoiceDataList": [],
            "ColorTextInfoList": []
        },
        {
            "Name": "谷水琴蕾",
            "Text": "呵呵……做得好，拥有纯真灵魂的人啊。",
            "ChoiceDataList": [],
            "ColorTextInfoList": []
        },
        {
            "Name": "谷水琴蕾",
            "Text": "果然跟我预料的一样……\n你成功克服十二项考验，\n得到了强韧的肉体……",
            "ChoiceDataList": [],
            "ColorTextInfoList": []
        },
        {
            "Name": "伏特加",
            "Text": "谢谢前辈！\n嘿嘿！这都是多亏了阿琴前辈的帮助！",
            "ChoiceDataList": [],
            "ColorTextInfoList": []
        },
        {
            "Name": "伏特加",
            "Text": "我照前辈说的去做，\n结果就变得这么强了！\n阿琴前辈果然很厉害！",
            "ChoiceDataList": [],
            "ColorTextInfoList": []
        },
        {
            "Name": "谷水琴蕾",
            "Text": "……不，吾传授的一切都是\n引领吾的北极星盟约。",
            "ChoiceDataList": [],
            "ColorTextInfoList": []
        },
        {
            "Name": "谷水琴蕾",
            "Text": "世界的看守者辛勤工作，仔细倾听地上的声音，\n睡眠时间甚至比鸟类短暂。\n有个人如世界的看守者般一直看着我、支持我……",
            "ChoiceDataList": [],
            "ColorTextInfoList": []
        },
        {
            "Name": "伏特加",
            "Text": "哦～！这个人好厉害喔！！\n是……阿琴前辈的弟弟吗？\n不对，应该是死党吧？",
            "ChoiceDataList": [],
            "ColorTextInfoList": []
        },
        {
            "Name": "谷水琴蕾",
            "Text": "不是，那家伙是少数能够理解吾的人。\n也可以说是保证会与这个世界为敌的\n独一无二的共犯。",
            "ChoiceDataList": [],
            "ColorTextInfoList": []
        },
        {
            "Name": "谷水琴蕾",
            "Text": "一样是追求刹那、渴求破坏，\n挑战比赛的人……！",
            "ChoiceDataList": [],
            "ColorTextInfoList": []
        },
        {
            "Name": "伏特加",
            "Text": "比赛……？\n啊！是训练员！？",
            "ChoiceDataList": [],
            "ColorTextInfoList": []
        },
        {
            "Name": "伏特加",
            "Text": "原来是训练员～！训练员教得很好耶！\n好帅──！你们的情谊感觉很火热！",
            "ChoiceDataList": [],
            "ColorTextInfoList": []
        },
        {
            "Name": "谷水琴蕾",
            "Text": "呵呵呵……“情谊”吗……？\n嗯，吾等或许被命运的锁链绑在一起呢。",
            "ChoiceDataList": [],
            "ColorTextInfoList": []
        },
        {
            "Name": "谷水琴蕾",
            "Text": "我要带着那家伙前往破坏彼端的理想乡。\n在抵达之前……\n我绝对不会放手……！",
            "ChoiceDataList": [],
            "ColorTextInfoList": []
        }
    ]
}