{
    "Title": "皋月赏结束后．3",
    "TextBlockList": [
        {
            "Name": "",
            "Text": "",
            "ChoiceDataList": [],
            "ColorTextInfoList": []
        },
        {
            "Name": "空中神宫",
            "Text": "……唔。",
            "ChoiceDataList": [],
            "ColorTextInfoList": []
        },
        {
            "Name": "空中神宫",
            "Text": "（结果如同“Parcae”显示。\n我赢了……我赢了，但是……）",
            "ChoiceDataList": [],
            "ColorTextInfoList": []
        },
        {
            "Name": "空中神宫",
            "Text": "（──不该是“这个”赢法！）",
            "ChoiceDataList": [],
            "ColorTextInfoList": []
        },
        {
            "Name": "空中神宫",
            "Text": "（原本有种注定好的胜利模式。\n我却没有以那“最佳路线”获得优胜。）",
            "ChoiceDataList": [],
            "ColorTextInfoList": []
        },
        {
            "Name": "空中神宫",
            "Text": "也就是说……！",
            "ChoiceDataList": [],
            "ColorTextInfoList": []
        },
        {
            "Name": "观众们",
            "Text": "咦！？空中神宫已经走掉了？\n这可是“皋月赏”耶！？",
            "ChoiceDataList": [],
            "ColorTextInfoList": []
        },
        {
            "Name": "观众们",
            "Text": "她赢了都不会高兴吗？\n咦咦……让人有点惊讶。",
            "ChoiceDataList": [],
            "ColorTextInfoList": []
        },
        {
            "Name": "独白",
            "Text": "恐怕是出现了在她预期外──\n也就是不在“Parcae”计算内的事情。",
            "ChoiceDataList": [
                "（得去找她才行！）"
            ],
            "ColorTextInfoList": []
        },
        {
            "Name": "独白",
            "Text": "我急忙追上空中神宫……\n却看到她不发一语地喘着气，\n双眼直盯着电脑画面。",
            "ChoiceDataList": [],
            "ColorTextInfoList": []
        },
        {
            "Name": "空中神宫",
            "Text": "……唉～～～～",
            "ChoiceDataList": [
                "空中神宫……"
            ],
            "ColorTextInfoList": []
        },
        {
            "Name": "空中神宫",
            "Text": "又来了。",
            "ChoiceDataList": [
                "咦？"
            ],
            "ColorTextInfoList": []
        },
        {
            "Name": "空中神宫",
            "Text": "答案又变了。",
            "ChoiceDataList": [],
            "ColorTextInfoList": []
        },
        {
            "Name": "空中神宫",
            "Text": "七公分……缩短成三公分了。",
            "ChoiceDataList": [
                "……！"
            ],
            "ColorTextInfoList": []
        },
        {
            "Name": "空中神宫",
            "Text": "还剩三公分……就剩三公分……\n只要这数字能化为零──",
            "ChoiceDataList": [],
            "ColorTextInfoList": []
        },
        {
            "Name": "空中神宫",
            "Text": "……唔。",
            "ChoiceDataList": [],
            "ColorTextInfoList": []
        },
        {
            "Name": "空中神宫",
            "Text": "呼……等等，等等。",
            "ChoiceDataList": [],
            "ColorTextInfoList": []
        },
        {
            "Name": "空中神宫",
            "Text": "虽然缩短了，但只是\n在“最佳路线”下的数字缩短了。",
            "ChoiceDataList": [],
            "ColorTextInfoList": []
        },
        {
            "Name": "空中神宫",
            "Text": "它并没有变成零。\n而且，这模式也可能是先在“皋月赏”获胜，\n接着在“日本打比”和“菊花赏”落败。",
            "ChoiceDataList": [],
            "ColorTextInfoList": []
        },
        {
            "Name": "空中神宫",
            "Text": "那么不管怎样，\n都是“死路一条”。",
            "ChoiceDataList": [],
            "ColorTextInfoList": []
        },
        {
            "Name": "空中神宫",
            "Text": "我要先将自己提升到\n预计以七公分的差距落败的理论值，\n然后重新寻找能将数值归零的要素……",
            "ChoiceDataList": [],
            "ColorTextInfoList": []
        },
        {
            "Name": "空中神宫",
            "Text": "你先回去。",
            "ChoiceDataList": [],
            "ColorTextInfoList": []
        },
        {
            "Name": "独白",
            "Text": "我都还没出声回应，空中神宫便走掉了。\n大概是想找个能够专心整理思绪的地方吧。\n当我这么想的时候──",
            "ChoiceDataList": [],
            "ColorTextInfoList": []
        },
        {
            "Name": "观众A",
            "Text": "刚才你看到了吗？她平常果然也是那个样子……\n该说有点我行我素吗？",
            "ChoiceDataList": [],
            "ColorTextInfoList": []
        },
        {
            "Name": "观众B",
            "Text": "大家都鼓掌了说。\n嗯～以后她会成为主角级选手吗……",
            "ChoiceDataList": [
                "（……不行，我不该插嘴）"
            ],
            "ColorTextInfoList": []
        },
        {
            "Name": "空中神宫",
            "Text": "……只要能改变那七公分，\n不管是什么样的噪声都会消失。",
            "ChoiceDataList": [],
            "ColorTextInfoList": []
        },
        {
            "Name": "独白",
            "Text": "之后在“日本打比”上，\n空中神宫也一定会展现成果。\n到时候，周遭对她的印象应该也会有所改变。",
            "ChoiceDataList": [
                "（最重要的是，她的实力是货真价实的）"
            ],
            "ColorTextInfoList": []
        },
        {
            "Name": "独白",
            "Text": "只要接下来她在大型赛事继续接连得胜，\n大家一定能明白她的魅力──",
            "ChoiceDataList": [],
            "ColorTextInfoList": []
        },
        {
            "Name": "空中神宫",
            "Text": "……真的开始改变了吗？",
            "ChoiceDataList": [],
            "ColorTextInfoList": []
        },
        {
            "Name": "空中神宫",
            "Text": "（我不会再梦见……那个糟透的恶梦。\n要结束了，结束之后再重新开始……）",
            "ChoiceDataList": [],
            "ColorTextInfoList": []
        },
        {
            "Name": "空中神宫",
            "Text": "（现在只剩三公分。\n只要这数字能化为零，我就……）",
            "ChoiceDataList": [],
            "ColorTextInfoList": []
        },
        {
            "Name": "独白",
            "Text": "──可是……如果这三公分\n不再缩短怎么办？",
            "ChoiceDataList": [],
            "ColorTextInfoList": []
        },
        {
            "Name": "独白",
            "Text": "如果宿命不变，\n我只是空欢喜一场的话……",
            "ChoiceDataList": [],
            "ColorTextInfoList": []
        },
        {
            "Name": "空中神宫",
            "Text": "……！！",
            "ChoiceDataList": [],
            "ColorTextInfoList": []
        },
        {
            "Name": "空中神宫",
            "Text": "不、不……不。",
            "ChoiceDataList": [],
            "ColorTextInfoList": []
        },
        {
            "Name": "空中神宫",
            "Text": "（我要努力思考，绞尽脑汁，找出各种方法。\n虽然现在还看不见胜利女神的尾巴，但是──）",
            "ChoiceDataList": [],
            "ColorTextInfoList": []
        },
        {
            "Name": "空中神宫",
            "Text": "就算是来硬的，\n我也要抓住那尾巴，让它属于我……！",
            "ChoiceDataList": [],
            "ColorTextInfoList": []
        },
        {
            "Name": "空中神宫",
            "Text": "等著吧……\n“日本打比”！",
            "ChoiceDataList": [],
            "ColorTextInfoList": []
        }
    ]
}