{
    "Title": "赢得录取资格吧！",
    "TextBlockList": [
        {
            "Name": "",
            "Text": "",
            "ChoiceDataList": [],
            "ColorTextInfoList": []
        },
        {
            "Name": "黄金船",
            "Text": "──要开始啰！\n测试你们的智慧、体力和凡得瓦力的\n终极考验！",
            "ChoiceDataList": [],
            "ColorTextInfoList": []
        },
        {
            "Name": "目白麦昆",
            "Text": "你、你到底……\n是想开始什么啊……！？",
            "ChoiceDataList": [],
            "ColorTextInfoList": []
        },
        {
            "Name": "",
            "Text": "回溯到几个小时前──\n我们碰巧被黄金船看见，\n然后被带到了河边。",
            "ChoiceDataList": [],
            "ColorTextInfoList": []
        },
        {
            "Name": "黄金船",
            "Text": "我要评估你们是否有资格参与我的计划，\n所以要让你们参加“面谈”──",
            "ChoiceDataList": [],
            "ColorTextInfoList": []
        },
        {
            "Name": "目白麦昆",
            "Text": "面、面谈……？计划……？\n话说你的目的到底是什么？",
            "ChoiceDataList": [],
            "ColorTextInfoList": []
        },
        {
            "Name": "黄金船",
            "Text": "──我不是正要开始说吗？\n让全阿船感动落泪，\n一个伫立在公园的孤独少年的故事。",
            "ChoiceDataList": [],
            "ColorTextInfoList": []
        },
        {
            "Name": "黄金船",
            "Text": "他好像是最近才刚搬来这里，\n但个性内向的他……就算看到其他小孩在玩，\n也无法主动去说想要加入……！",
            "ChoiceDataList": [],
            "ColorTextInfoList": []
        },
        {
            "Name": "黄金船",
            "Text": "孤独究竟为他年幼的心灵带来多大的痛苦……！\n即使是单分子线，只有一条还是不够用的！\n我实在很想替他做点什么……！",
            "ChoiceDataList": [],
            "ColorTextInfoList": []
        },
        {
            "Name": "目白麦昆",
            "Text": "你、你冷静一点……不过，\n感觉你的目的比我想像中还要正常……？",
            "ChoiceDataList": [],
            "ColorTextInfoList": []
        },
        {
            "Name": "黄金船",
            "Text": "为了从背后推那个少年一把，\n我需要愿意帮忙的同志。\n这样你们明白我为何要举行面谈了吧？",
            "ChoiceDataList": [],
            "ColorTextInfoList": []
        },
        {
            "Name": "目白麦昆",
            "Text": "嗯、嗯……如果是为了这种事，\n那我也无法拒绝……",
            "ChoiceDataList": [],
            "ColorTextInfoList": []
        },
        {
            "Name": "",
            "Text": "于是，我和目白麦昆一起\n接受了黄金船的“面谈”──",
            "ChoiceDataList": [],
            "ColorTextInfoList": []
        },
        {
            "Name": "目白麦昆",
            "Text": "呼……呼……！\n为、为什么……\n必须要爬上悬崖啊……！",
            "ChoiceDataList": [],
            "ColorTextInfoList": []
        },
        {
            "Name": "黄金船",
            "Text": "这还用问吗？大家不是都说\n狮子会把自己的小孩推下悬崖吗？",
            "ChoiceDataList": [],
            "ColorTextInfoList": []
        },
        {
            "Name": "目白麦昆",
            "Text": "你根本就没解释到任何事情！\n而且这哪里是面谈了！？",
            "ChoiceDataList": [],
            "ColorTextInfoList": []
        },
        {
            "Name": "黄金船",
            "Text": "呜呜……拜托你了！我真的需要帮手！\n这都是为了那个孤独地待在离岛，\n等独生子回来的老奶奶……！",
            "ChoiceDataList": [],
            "ColorTextInfoList": []
        },
        {
            "Name": "目白麦昆",
            "Text": "你不是要拯救公园的男孩子吗！？",
            "ChoiceDataList": [],
            "ColorTextInfoList": []
        },
        {
            "Name": "目白麦昆",
            "Text": "轰出去～拿下比赛吧～！\n轰到场外～战无不胜～你是最强的～！",
            "ChoiceDataList": [],
            "ColorTextInfoList": []
        },
        {
            "Name": "黄金船",
            "Text": "喂，再大声一点！\n这么小声，操场的人根本听不见～！",
            "ChoiceDataList": [],
            "ColorTextInfoList": []
        },
        {
            "Name": "目白麦昆",
            "Text": "帮～助～小～孩～子～！\n和～大～声～喊～话～！\n到～底有什么关系啊～～～～！？！？",
            "ChoiceDataList": [],
            "ColorTextInfoList": []
        },
        {
            "Name": "黄金船",
            "Text": "这还用说吗？为了拯救充满回忆的\n古早味零食店，需要干劲十足的加油声啊！",
            "ChoiceDataList": [],
            "ColorTextInfoList": []
        },
        {
            "Name": "目白麦昆",
            "Text": "你～的～目的，是不是又变了～～！？！？",
            "ChoiceDataList": [],
            "ColorTextInfoList": []
        },
        {
            "Name": "黄金船",
            "Text": "──好～你们很努力呢！\n你们都顺利被录取了！",
            "ChoiceDataList": [],
            "ColorTextInfoList": []
        },
        {
            "Name": "目白麦昆",
            "Text": "呼、呼……就算你这么说，\n我已经连你的目的是什么都搞不清楚了……！？",
            "ChoiceDataList": [],
            "ColorTextInfoList": []
        },
        {
            "Name": "黄金船",
            "Text": "啊！？我不是说过要帮少年鼓起勇气吗？\n而且，方法就只有一个！",
            "ChoiceDataList": [],
            "ColorTextInfoList": []
        },
        {
            "Name": "黄金船",
            "Text": "──创业！我要设立一个\n炒面摊贩股份有限公司！！！！",
            "ChoiceDataList": [],
            "ColorTextInfoList": []
        },
        {
            "Name": "目白麦昆",
            "Text": "为什么！？！？",
            "ChoiceDataList": [
                "要和孩子们一起玩模仿摊贩的游戏吗？",
                "原来如此……是这么回事啊"
            ],
            "ColorTextInfoList": []
        },
        {
            "Name": "黄金船",
            "Text": "喂，开什么玩笑！\n我可是认真想要炒面的！\n你居然说这是在“模仿”！？",
            "ChoiceDataList": [],
            "ColorTextInfoList": []
        },
        {
            "Name": "黄金船",
            "Text": "看来你们还没做好心理准备！\n开始举办第二次面谈吧！",
            "ChoiceDataList": [],
            "ColorTextInfoList": []
        },
        {
            "Name": "目白麦昆",
            "Text": "所以说，为什么是炒面啊！？\n我也搞不懂进行面谈的意义！",
            "ChoiceDataList": [],
            "ColorTextInfoList": []
        },
        {
            "Name": "",
            "Text": "……在那之后，我们继续配合黄金船\n进行名为“面谈”的神秘测试……",
            "ChoiceDataList": [],
            "ColorTextInfoList": []
        },
        {
            "Name": "黄金船",
            "Text": "没错。就是蝴蝶效应产生的\n薛定谔方程式。",
            "ChoiceDataList": [
                "温带低气压的革命啊……"
            ],
            "ColorTextInfoList": []
        },
        {
            "Name": "黄金船",
            "Text": "你很懂嘛！\n透过削减水冷式引擎和免洗筷的数量，\n也把解决资源问题纳入考量吧！",
            "ChoiceDataList": [],
            "ColorTextInfoList": []
        },
        {
            "Name": "目白麦昆",
            "Text": "……请等一下！？\n为什么要塑造出只有你们两人\n明白状况的气氛！？听我说话啊！？",
            "ChoiceDataList": [],
            "ColorTextInfoList": []
        }
    ]
}