{
    "Title": "高松宫纪念结束后．全新的我以及梦想",
    "TextBlockList": [
        {
            "Name": "",
            "Text": "",
            "ChoiceDataList": [],
            "ColorTextInfoList": []
        },
        {
            "Name": "观众A",
            "Text": "天啊～！真是太快了～！\n好有魄力啊！\n短途赛就是这点好！",
            "ChoiceDataList": [],
            "ColorTextInfoList": []
        },
        {
            "Name": "观众B",
            "Text": "而且啊……西野花跑起来\n好像跟以前不太一样了呢。",
            "ChoiceDataList": [],
            "ColorTextInfoList": []
        },
        {
            "Name": "观众B",
            "Text": "之前是觉得她“跑得好快！”\n但她好像比以前更有力了？\n该不会……她正在进化──",
            "ChoiceDataList": [],
            "ColorTextInfoList": []
        },
        {
            "Name": "",
            "Text": "我想眼光锐利的观众及评论家\n应该都感觉到她的跑法改变了吧。\n接下来我们还会继续摸索尝试，不过目前──",
            "ChoiceDataList": [
                "实际比赛过后觉得如何？"
            ],
            "ColorTextInfoList": []
        },
        {
            "Name": "西野花",
            "Text": "这个嘛……",
            "ChoiceDataList": [],
            "ColorTextInfoList": []
        },
        {
            "Name": "西野花",
            "Text": "还有一些需要检讨的地方……\n不过我认为自己已经尽力了。",
            "ChoiceDataList": [
                "我观战时也感觉到你有所不同了！"
            ],
            "ColorTextInfoList": []
        },
        {
            "Name": "西野花",
            "Text": "真的吗？\n太好了……",
            "ChoiceDataList": [
                "看来跑短距离没有问题啊",
                "看来跑短距离没有问题呢"
            ],
            "ColorTextInfoList": []
        },
        {
            "Name": "西野花",
            "Text": "是啊。\n看来我果然适合短距离。",
            "ChoiceDataList": [],
            "ColorTextInfoList": []
        },
        {
            "Name": "西野花",
            "Text": "那下一场目标竞赛，\n就照这样继续挑战短距离吗？",
            "ChoiceDataList": [
                "继续挑战短距离是不错……"
            ],
            "ColorTextInfoList": []
        },
        {
            "Name": "",
            "Text": "以理想状况来说，若她能克服更长一点的距离，\n能挑战的重赏比赛也会增加，\n这样就能拓展她的活跃范围。",
            "ChoiceDataList": [],
            "ColorTextInfoList": []
        },
        {
            "Name": "",
            "Text": "只要她的身体能成长，\n未来能力也有所提升，\n增加挑战距离也未尝不好。",
            "ChoiceDataList": [],
            "ColorTextInfoList": []
        },
        {
            "Name": "",
            "Text": "我们出席了比赛后的记者会。\n在记者会上，我们发表了\n西野花下次将参加的比赛。",
            "ChoiceDataList": [
                "下一个目标是“英里跑者杯”"
            ],
            "ColorTextInfoList": []
        },
        {
            "Name": "记者A",
            "Text": "喔喔，英里赛啊！\n既然要前进“英里跑者杯”，\n那再接下来就是……",
            "ChoiceDataList": [
                "预计也会挑战GⅠ“安田纪念”"
            ],
            "ColorTextInfoList": [
                "英里跑者杯"
            ]
        },
        {
            "Name": "记者A",
            "Text": "你们果然打算挑战GⅠ呢。\n请问接下来，有可能挑战中距离吗？",
            "ChoiceDataList": [
                "目前无可奉告"
            ],
            "ColorTextInfoList": []
        },
        {
            "Name": "记者A",
            "Text": "唔，这样啊……\n也对，光是以现状来看，\n西野花也一路缔造了许多亮眼成绩呢。",
            "ChoiceDataList": [],
            "ColorTextInfoList": []
        },
        {
            "Name": "记者A",
            "Text": "只要能继续维持下去，\n不只西野花，训练员应该也有机会\n受到URA表扬吧？",
            "ChoiceDataList": [],
            "ColorTextInfoList": []
        },
        {
            "Name": "西野花",
            "Text": "……！",
            "ChoiceDataList": [
                "我从未想过自己能受表扬"
            ],
            "ColorTextInfoList": []
        },
        {
            "Name": "记者A",
            "Text": "啊哈哈，真是失礼了。\n不过，要是哪天两位真的得奖，\n请务必让我们媒体也一同庆祝致意。",
            "ChoiceDataList": [],
            "ColorTextInfoList": []
        },
        {
            "Name": "西野花",
            "Text": "好、好的……！\n谢谢各位。",
            "ChoiceDataList": [],
            "ColorTextInfoList": []
        },
        {
            "Name": "",
            "Text": "记者会结束后──",
            "ChoiceDataList": [
                "那我先去外面等你喔"
            ],
            "ColorTextInfoList": []
        },
        {
            "Name": "西野花",
            "Text": "好的！",
            "ChoiceDataList": [],
            "ColorTextInfoList": []
        },
        {
            "Name": "西野花",
            "Text": "──表扬啊……",
            "ChoiceDataList": [],
            "ColorTextInfoList": []
        },
        {
            "Name": "西野花",
            "Text": "（这么说也对，受到肯定也就等于……\n有机会得奖。\n这是非常光荣的一件事……）",
            "ChoiceDataList": [],
            "ColorTextInfoList": []
        },
        {
            "Name": "西野花",
            "Text": "对训练员来说，\n应该是非常值得高兴的事吧……",
            "ChoiceDataList": [],
            "ColorTextInfoList": []
        },
        {
            "Name": "西野花",
            "Text": "（太棒了，搞不好……\n我能够替训练员缔造未来。）",
            "ChoiceDataList": [],
            "ColorTextInfoList": []
        },
        {
            "Name": "西野花",
            "Text": "（既然这样，我要继续拼命努力……\n帮助训练员得奖！）",
            "ChoiceDataList": [],
            "ColorTextInfoList": []
        },
        {
            "Name": "西野花",
            "Text": "……嘿嘿。\n我找到新的梦想了……♪",
            "ChoiceDataList": [],
            "ColorTextInfoList": []
        },
        {
            "Name": "樱花进王",
            "Text": "啊，找到你啦，小花同学！\n今天比赛辛苦了──！",
            "ChoiceDataList": [],
            "ColorTextInfoList": []
        },
        {
            "Name": "西野花",
            "Text": "啊，是爆──",
            "ChoiceDataList": [],
            "ColorTextInfoList": []
        },
        {
            "Name": "樱花进王",
            "Text": "我看了你的记者会喔──！\n挑战英里赛啊……真是足以作为模范的目标！",
            "ChoiceDataList": [],
            "ColorTextInfoList": []
        },
        {
            "Name": "樱花进王",
            "Text": "我也打算要称霸所有阶级，\n但很遗憾，目前我正忙于\n追求极致的速度！",
            "ChoiceDataList": [],
            "ColorTextInfoList": []
        },
        {
            "Name": "樱花进王",
            "Text": "下次就在秋天的“短途马锦标”上见了！\n再会！！",
            "ChoiceDataList": [],
            "ColorTextInfoList": []
        },
        {
            "Name": "西野花",
            "Text": "──进王……",
            "ChoiceDataList": [],
            "ColorTextInfoList": []
        },
        {
            "Name": "也文摄辉",
            "Text": "她还是一样，快如疾风呢。\n看到她这样，没人会说樱花很梦幻飘渺了吧。",
            "ChoiceDataList": [],
            "ColorTextInfoList": []
        },
        {
            "Name": "西野花",
            "Text": "啊哈哈，就是啊。",
            "ChoiceDataList": [],
            "ColorTextInfoList": []
        },
        {
            "Name": "也文摄辉",
            "Text": "……小花，\n你也打算挑战英里赛呀？",
            "ChoiceDataList": [],
            "ColorTextInfoList": []
        },
        {
            "Name": "西野花",
            "Text": "是的，我希望自己能够一点一点\n增加挑战距离。",
            "ChoiceDataList": [],
            "ColorTextInfoList": []
        },
        {
            "Name": "也文摄辉",
            "Text": "一点一点……",
            "ChoiceDataList": [],
            "ColorTextInfoList": []
        },
        {
            "Name": "也文摄辉",
            "Text": "……“距离”之墙高耸，狠狠阻挡着挑战者，\n就连暴风雨也不禁胆怯。",
            "ChoiceDataList": [],
            "ColorTextInfoList": []
        },
        {
            "Name": "西野花",
            "Text": "摄辉……？",
            "ChoiceDataList": [],
            "ColorTextInfoList": []
        },
        {
            "Name": "也文摄辉",
            "Text": "我也会参加“英里跑者杯”。\n我会在短距离、在英里赛，化为一阵风。而且──",
            "ChoiceDataList": [],
            "ColorTextInfoList": []
        },
        {
            "Name": "也文摄辉",
            "Text": "我也打算在更长距离的比赛中保持领先……\n我打算……“称霸三阶级”。",
            "ChoiceDataList": [],
            "ColorTextInfoList": []
        },
        {
            "Name": "西野花",
            "Text": "……！",
            "ChoiceDataList": [],
            "ColorTextInfoList": []
        },
        {
            "Name": "也文摄辉",
            "Text": "……看了你的记者会，\n我心中吹起了狂风暴雨。",
            "ChoiceDataList": [],
            "ColorTextInfoList": []
        },
        {
            "Name": "也文摄辉",
            "Text": "不过，现在似乎\n终于平静下来了……",
            "ChoiceDataList": [],
            "ColorTextInfoList": []
        },
        {
            "Name": "西野花",
            "Text": "……摄辉给人的感觉\n好像跟平常不太一样。",
            "ChoiceDataList": [],
            "ColorTextInfoList": []
        },
        {
            "Name": "西野花",
            "Text": "她究竟发生了什么事呢……？",
            "ChoiceDataList": [
                "到时在“英里跑者C”上或许会有所发现",
                "到时在“英里跑者C”上或许会有所发现"
            ],
            "ColorTextInfoList": []
        },
        {
            "Name": "",
            "Text": "也文摄辉的状况很令人在意，\n但我们还是先朝着目标前进，\n重新展开日复一日的训练。",
            "ChoiceDataList": [],
            "ColorTextInfoList": []
        }
    ]
}