{
    "Title": "不会输给劲敌的",
    "TextBlockList": [
        {
            "Name": "",
            "Text": "",
            "ChoiceDataList": [],
            "ColorTextInfoList": []
        },
        {
            "Name": "独白",
            "Text": "伙伴增加后，双涡轮“胆小”的问题解决了。\n但她却在模拟赛连吃败仗。\n另一方面──",
            "ChoiceDataList": [],
            "ColorTextInfoList": []
        },
        {
            "Name": "独白",
            "Text": "东海帝王的出道也迟迟定不下来。\n为参加经典三冠一事蒙上阴霾……\n但她本人没有放弃，仍持续努力着。",
            "ChoiceDataList": [],
            "ColorTextInfoList": [
                "经典"
            ]
        },
        {
            "Name": "独白",
            "Text": "双涡轮因为她锲而不舍的精神受到刺激。\n心中再一次点燃了火焰。",
            "ChoiceDataList": [],
            "ColorTextInfoList": []
        }
    ]
}