{
  "Title": "Sternstunde",
  "TextBlockList": [
    {
      "Name": "",
      "Text": "",
      "ChoiceDataList": [],
      "ColorTextInfoList": []
    },
    {
      "Name": "独白",
      "Text": "然后，迎来了选拔赛当天――",
      "ChoiceDataList": [],
      "ColorTextInfoList": []
    },
    {
      "Name": "独白",
      "Text": "荣进闪耀正在为参加下一场1600m比赛做准备。\r\n她身体好像没什么问题了，只是总是东张西望的……",
      "ChoiceDataList": [],
      "ColorTextInfoList": []
    },
    {
      "Name": "荣进闪耀",
      "Text": "啊……",
      "ChoiceDataList": [],
      "ColorTextInfoList": []
    },
    {
      "Name": "独白",
      "Text": "我顺着她的视线停留处看去，是一对外国人夫妇。\r\n他们似乎就是荣进闪耀的父母，认真的神情有些相似。",
      "ChoiceDataList": [],
      "ColorTextInfoList": []
    },
    {
      "Name": "荣进闪耀",
      "Text": "……呼。\r\ntoi,toi,toi……――",
      "ChoiceDataList": [],
      "ColorTextInfoList": []
    },
    {
      "Name": "学园工作人员A",
      "Text": "到时间了！\r\n参加1600m赛的各位选手，请来集合！",
      "ChoiceDataList": [],
      "ColorTextInfoList": []
    },
    {
      "Name": "荣进闪耀",
      "Text": "……Auf geht's！\r\n（走吧！）",
      "ChoiceDataList": [],
      "ColorTextInfoList": []
    },
    {
      "Name": "独白",
      "Text": "就这样，在父母的注视下，荣进闪耀的选拔赛开始了。\r\n结果是――",
      "ChoiceDataList": [],
      "ColorTextInfoList": []
    },
    {
      "Name": "荣进闪耀",
      "Text": "――啊……训练员。\r\n果然，您也来看比赛了呢。",
      "ChoiceDataList": [
        "辛苦了"
      ],
      "ColorTextInfoList": []
    },
    {
      "Name": "荣进闪耀",
      "Text": "……非常感谢。",
      "ChoiceDataList": [],
      "ColorTextInfoList": []
    },
    {
      "Name": "独白",
      "Text": "她的表情有点阴沉，但也没办法。最终荣进闪耀只以第6名\r\n的成绩结束了选拔赛。不过――",
      "ChoiceDataList": [
        "你跑得很好",
        "你跑得很好"
      ],
      "ColorTextInfoList": []
    },
    {
      "Name": "荣进闪耀",
      "Text": "不。应该不能用『可以』或『不可以』来形容。\r\n第6名就已经说明了一切。",
      "ChoiceDataList": [
        "但你的跑法未来可期"
      ],
      "ColorTextInfoList": []
    },
    {
      "Name": "荣进闪耀",
      "Text": "……果然您跟我看待事物的方式完全不同呢。\r\n正因如此……――",
      "ChoiceDataList": [],
      "ColorTextInfoList": []
    },
    {
      "Name": "荣进闪耀",
      "Text": "那个，我有一个请求。这之后，我要跟父母见面……\r\n您能和我一起来吗？",
      "ChoiceDataList": [
        "可以吗？",
        "可以吗？"
      ],
      "ColorTextInfoList": []
    },
    {
      "Name": "荣进闪耀",
      "Text": "可以。已经变成了这样的结果……\r\n我没有了轻松讲出来话的自信。但是――",
      "ChoiceDataList": [],
      "ColorTextInfoList": []
    },
    {
      "Name": "荣进闪耀",
      "Text": "以前您说过，『心情能够传达』。\r\n所以说……那个。",
      "ChoiceDataList": [
        "我知道了，走吧"
      ],
      "ColorTextInfoList": []
    },
    {
      "Name": "荣进闪耀",
      "Text": "……！\r\n非常感谢――",
      "ChoiceDataList": [],
      "ColorTextInfoList": []
    },
    {
      "Name": "独白",
      "Text": "荣进闪耀的父母并肩等待着她。\r\n目光看到了他们二人后，她停下了脚步――",
      "ChoiceDataList": [],
      "ColorTextInfoList": []
    },
    {
      "Name": "荣进闪耀",
      "Text": "……",
      "ChoiceDataList": [],
      "ColorTextInfoList": []
    },
    {
      "Name": "独白",
      "Text": "她不安地看着我，我点点头鼓励她。\r\n于是她像下定了决心一样，踏出了一步――",
      "ChoiceDataList": [],
      "ColorTextInfoList": []
    },
    {
      "Name": "荣进闪耀",
      "Text": "『父亲、母亲。好久不见。\r\n你们能如约来看我的比赛，非常感谢。』",
      "ChoiceDataList": [],
      "ColorTextInfoList": []
    },
    {
      "Name": "荣进闪耀",
      "Text": "『然而，我却没能遵守约定。作为你们二人的女儿，我想\r\n展示出我在正确的成长。……那个，我――』",
      "ChoiceDataList": [],
      "ColorTextInfoList": []
    },
    {
      "Name": "闪耀的母亲",
      "Text": "『闪耀，你很努力啊。』",
      "ChoiceDataList": [],
      "ColorTextInfoList": []
    },
    {
      "Name": "荣进闪耀",
      "Text": "诶……",
      "ChoiceDataList": [],
      "ColorTextInfoList": []
    },
    {
      "Name": "闪耀的父亲",
      "Text": "『嗯。虽然结果并不完美，但我们看到了你努力的痕迹。\r\n以前你总会过于拼命，但现在能抑制住了呢。』",
      "ChoiceDataList": [],
      "ColorTextInfoList": []
    },
    {
      "Name": "闪耀的父亲",
      "Text": "『你有在为了我们而拼命努力吧？你好好地遵从了教导。\r\n作为父母，我们感到骄傲。』",
      "ChoiceDataList": [],
      "ColorTextInfoList": []
    },
    {
      "Name": "闪耀的父亲",
      "Text": "『谢谢你让我们高兴。我们的Schatzi*……』\r\n（*心肝宝贝）",
      "ChoiceDataList": [],
      "ColorTextInfoList": []
    },
    {
      "Name": "荣进闪耀",
      "Text": "……！",
      "ChoiceDataList": [],
      "ColorTextInfoList": []
    },
    {
      "Name": "荣进闪耀",
      "Text": "（我想起来了。圣诞节的时候，父亲他……）",
      "ChoiceDataList": [],
      "ColorTextInfoList": []
    },
    {
      "Name": "闪耀的父亲",
      "Text": "『闪耀，我们的Schatzi。千万不要忘记啊。\r\n我不容许有误差的理由，当然是为了品质。』",
      "ChoiceDataList": [],
      "ColorTextInfoList": []
    },
    {
      "Name": "闪耀的父亲",
      "Text": "『但更为重要的是――为了他人的幸福，\r\n正确地去做自己应该做的事。』",
      "ChoiceDataList": [],
      "ColorTextInfoList": []
    },
    {
      "Name": "小时候的闪耀",
      "Text": "『为了，他人的幸福……？』",
      "ChoiceDataList": [],
      "ColorTextInfoList": []
    },
    {
      "Name": "闪耀的父亲",
      "Text": "『不然，只是照着食谱的话谁都可以来做。\r\n正因为我们用心地去做，才有了我们来做的意义。』",
      "ChoiceDataList": [],
      "ColorTextInfoList": []
    },
    {
      "Name": "小时候的闪耀",
      "Text": "『但是，心是没有味道的哦？\r\n爸爸的食谱上也没写……』",
      "ChoiceDataList": [],
      "ColorTextInfoList": []
    },
    {
      "Name": "闪耀的父亲",
      "Text": "『呵呵……你说的对。你现在还不懂得其区别也没关系。\r\n总有一天――当你做了一份让自己骄傲的工作时，你就会\r\n明白的。』",
      "ChoiceDataList": [],
      "ColorTextInfoList": []
    },
    {
      "Name": "荣进闪耀",
      "Text": "（――不是只按照计划取得胜利就可以了。我为了他们二人\r\n想要成长的这份心，为他们带来了喜悦。）",
      "ChoiceDataList": [],
      "ColorTextInfoList": []
    },
    {
      "Name": "荣进闪耀",
      "Text": "（我过于害怕把一切都给打乱了。\r\n但是，不应该这样。真正重要的是――）",
      "ChoiceDataList": [],
      "ColorTextInfoList": []
    },
    {
      "Name": "荣进闪耀",
      "Text": "『……父亲、母亲。谢谢你们。\r\n我……有在努力了。』",
      "ChoiceDataList": [],
      "ColorTextInfoList": []
    },
    {
      "Name": "独白",
      "Text": "他们之间的谈话似乎结束了，荣进闪耀一脸愉悦，\r\n要我去跟她的父母打招呼。",
      "ChoiceDataList": [
        "那个……"
      ],
      "ColorTextInfoList": []
    },
    {
      "Name": "闪耀的父亲",
      "Text": "日语，没有问题。因为跟女儿一起学过，所以我稍微懂一点。\r\n闪耀，这个人是？",
      "ChoiceDataList": [],
      "ColorTextInfoList": []
    },
    {
      "Name": "荣进闪耀",
      "Text": "是我的训练员――",
      "ChoiceDataList": [
        "……！"
      ],
      "ColorTextInfoList": []
    },
    {
      "Name": "荣进闪耀",
      "Text": "……是，我考虑中的人。\r\n现在只是预定。",
      "ChoiceDataList": [],
      "ColorTextInfoList": []
    },
    {
      "Name": "独白",
      "Text": "因为太过突然，搞得我有些吃惊。但我倒也能理解。大概从\r\n我第一次遇到她的时候，她就已经下定决心了吧。所以――",
      "ChoiceDataList": [
        "我更正一下"
      ],
      "ColorTextInfoList": []
    },
    {
      "Name": "荣进闪耀",
      "Text": "……？",
      "ChoiceDataList": [
        "不是预定，我就是她的训练员。"
      ],
      "ColorTextInfoList": []
    },
    {
      "Name": "荣进闪耀",
      "Text": "……！",
      "ChoiceDataList": [],
      "ColorTextInfoList": []
    },
    {
      "Name": "闪耀的父亲",
      "Text": "……这样吗。我的女儿，就拜托您了。\r\n闪耀，要跟这个人，一起加油哦。",
      "ChoiceDataList": [],
      "ColorTextInfoList": []
    },
    {
      "Name": "荣进闪耀",
      "Text": "――是！",
      "ChoiceDataList": [],
      "ColorTextInfoList": []
    },
    {
      "Name": "荣进闪耀",
      "Text": "我做的日程是完美的，按照计划去进行\r\n也绝对不会有错。只是――",
      "ChoiceDataList": [],
      "ColorTextInfoList": []
    },
    {
      "Name": "荣进闪耀",
      "Text": "我还没有足够的实力去再现那些日程。\r\n我用不成熟的想法，把自己给逼上了绝路。",
      "ChoiceDataList": [],
      "ColorTextInfoList": []
    },
    {
      "Name": "荣进闪耀",
      "Text": "……我似乎是很笨拙，一旦偏离了我所画的线，\r\n就不知道该如何去修正。",
      "ChoiceDataList": [],
      "ColorTextInfoList": []
    },
    {
      "Name": "荣进闪耀",
      "Text": "所以，我需要有一个人从另一个角度\r\n去看看我画的线是否是笔直的。",
      "ChoiceDataList": [
        "那就是你选择我当训练员的理由？"
      ],
      "ColorTextInfoList": []
    },
    {
      "Name": "荣进闪耀",
      "Text": "是。……您，为什么会接受我呢？",
      "ChoiceDataList": [
        "是因为一见钟情吧"
      ],
      "ColorTextInfoList": []
    },
    {
      "Name": "荣进闪耀",
      "Text": "……诶！？\r\n一、一见钟情……？",
      "ChoiceDataList": [],
      "ColorTextInfoList": []
    },
    {
      "Name": "独白",
      "Text": "我与她那奔跑的身姿、那真挚的眼神相遇……\r\n我想把她那美丽的跑姿延伸到遥远的彼方。",
      "ChoiceDataList": [
        "这肯定是计划好了的吧"
      ],
      "ColorTextInfoList": []
    },
    {
      "Name": "荣进闪耀",
      "Text": "……！",
      "ChoiceDataList": [],
      "ColorTextInfoList": []
    },
    {
      "Name": "荣进闪耀",
      "Text": "……不，不可能会有那样的计划。\r\n至少在我心中是不存在的。",
      "ChoiceDataList": [
        "是、是吗"
      ],
      "ColorTextInfoList": []
    },
    {
      "Name": "荣进闪耀",
      "Text": "所以说，有必要进行一下修正呢。\r\n今后，我必须作为马娘继续奔跑。",
      "ChoiceDataList": [],
      "ColorTextInfoList": []
    },
    {
      "Name": "荣进闪耀",
      "Text": "我也会把您加入到我那份日程当中。\r\n――我们一起，做值得骄傲的工作吧。",
      "ChoiceDataList": [],
      "ColorTextInfoList": []
    },
    {
      "Name": "独白",
      "Text": "就这样，我与荣进闪耀以闪耀系列赛\r\n为目标的日子开始了。",
      "ChoiceDataList": [],
      "ColorTextInfoList": []
    }
  ]
}