{
    "Title": "夏季集训（第三年）开始！",
    "TextBlockList": [
        {
            "Name": "",
            "Text": "",
            "ChoiceDataList": [],
            "ColorTextInfoList": []
        },
        {
            "Name": "独白",
            "Text": "今年又来到了“夏季集训”的时间。\n黄金城市看起来非常雀跃。",
            "ChoiceDataList": [],
            "ColorTextInfoList": []
        },
        {
            "Name": "独白",
            "Text": "干劲十足的她想变得更强，\n好在“日本C”战胜强敌。\n于是火热的夏季集训开锣了！",
            "ChoiceDataList": [],
            "ColorTextInfoList": []
        }
    ]
}