{
    "Title": "有马纪念结束后．继续无止尽地吹拂吧",
    "TextBlockList": [
        {
            "Name": "",
            "Text": "",
            "ChoiceDataList": [],
            "ColorTextInfoList": []
        },
        {
            "Name": "实况",
            "Text": "获……获胜的是东海帝王……！\n称霸有马纪念的是东海帝王！",
            "ChoiceDataList": [],
            "ColorTextInfoList": []
        },
        {
            "Name": "实况",
            "Text": "东海帝王在这里……\n奇迹般地复活了……！！",
            "ChoiceDataList": [],
            "ColorTextInfoList": []
        },
        {
            "Name": "",
            "Text": "（喔喔喔喔喔！）",
            "ChoiceDataList": [],
            "ColorTextInfoList": []
        },
        {
            "Name": "帝王的粉丝们",
            "Text": "帝．皇！帝．皇！！\n帝．皇！帝．皇！！",
            "ChoiceDataList": [],
            "ColorTextInfoList": []
        },
        {
            "Name": "东海帝王",
            "Text": "呼────\n……唔，嘿嘿！！",
            "ChoiceDataList": [],
            "ColorTextInfoList": []
        },
        {
            "Name": "东海帝王",
            "Text": "大家────！！\n谢谢你们帮我加油────！！",
            "ChoiceDataList": [],
            "ColorTextInfoList": []
        },
        {
            "Name": "也文摄辉",
            "Text": "恭喜你，帝王。\n……是我彻底输了。",
            "ChoiceDataList": [],
            "ColorTextInfoList": []
        },
        {
            "Name": "东海帝王",
            "Text": "摄辉！\n嘻嘻嘻，谢啦！",
            "ChoiceDataList": [],
            "ColorTextInfoList": []
        },
        {
            "Name": "东海帝王",
            "Text": "……好棒喔，这个景色真的好棒。\n你跑赢“天皇赏（秋）”的时候，\n也是像现在这种感觉吗？",
            "ChoiceDataList": [],
            "ColorTextInfoList": []
        },
        {
            "Name": "东海帝王",
            "Text": "心情真的好好，好开心自己真的做到了！\n开心得忍不住一直笑出来──",
            "ChoiceDataList": [],
            "ColorTextInfoList": []
        },
        {
            "Name": "东海帝王",
            "Text": "但是又觉得这样根──本不够！",
            "ChoiceDataList": [],
            "ColorTextInfoList": []
        },
        {
            "Name": "也文摄辉",
            "Text": "！",
            "ChoiceDataList": [],
            "ColorTextInfoList": []
        },
        {
            "Name": "东海帝王",
            "Text": "而且，认真说起来的话，\n“超越皇帝！”这个目标，\n毕竟是被你给抢先了嘛。",
            "ChoiceDataList": [],
            "ColorTextInfoList": []
        },
        {
            "Name": "东海帝王",
            "Text": "所以今天这样就算是我一胜一败！\n我们之间还没分出胜负，对吧？",
            "ChoiceDataList": [],
            "ColorTextInfoList": []
        },
        {
            "Name": "也文摄辉",
            "Text": "帝王──\n呵呵，确实是这样没错。",
            "ChoiceDataList": [],
            "ColorTextInfoList": []
        },
        {
            "Name": "东海帝王",
            "Text": "那我们还是得分出个胜负来才行吧！",
            "ChoiceDataList": [],
            "ColorTextInfoList": []
        },
        {
            "Name": "东海帝王",
            "Text": "在下一场比赛决胜负。\n……对吧？摄辉。",
            "ChoiceDataList": [],
            "ColorTextInfoList": []
        },
        {
            "Name": "也文摄辉",
            "Text": "是的。\n……在下一场比赛决胜负。",
            "ChoiceDataList": [],
            "ColorTextInfoList": []
        },
        {
            "Name": "也文摄辉",
            "Text": "因为，风将永不止息地持续吹拂──",
            "ChoiceDataList": [],
            "ColorTextInfoList": []
        }
    ]
}