{
    "Title": "超越可爱的领域",
    "TextBlockList": [
        {
            "Name": "",
            "Text": "",
            "ChoiceDataList": [],
            "ColorTextInfoList": []
        },
        {
            "Name": "独白",
            "Text": "真机伶顺利地在闪耀系列赛中\n留下了出色的成绩。",
            "ChoiceDataList": [],
            "ColorTextInfoList": []
        },
        {
            "Name": "独白",
            "Text": "我们一起熬过了\n非常重要的“最初的三年”──",
            "ChoiceDataList": [],
            "ColorTextInfoList": []
        },
        {
            "Name": "独白",
            "Text": "当我还沉浸在度过巨大关卡的余韵中时，\n某天，发生了一件事。",
            "ChoiceDataList": [],
            "ColorTextInfoList": []
        },
        {
            "Name": "主持人",
            "Text": "──以上就是今年的年度代表赛马娘。\n接下来是……",
            "ChoiceDataList": [],
            "ColorTextInfoList": []
        },
        {
            "Name": "主持人",
            "Text": "这次因为特雷森学园理事长的提案，\n特别为某位赛马娘设立了一个新的奖项。",
            "ChoiceDataList": [],
            "ColorTextInfoList": [
                "特雷森学园"
            ]
        },
        {
            "Name": "主持人",
            "Text": "这位赛马娘为赛马娘界缔造了许多创举……",
            "ChoiceDataList": [],
            "ColorTextInfoList": []
        },
        {
            "Name": "主持人",
            "Text": "──真机伶，请上台！",
            "ChoiceDataList": [],
            "ColorTextInfoList": []
        },
        {
            "Name": "真机伶",
            "Text": "是♪",
            "ChoiceDataList": [],
            "ColorTextInfoList": []
        },
        {
            "Name": "秋川理事长",
            "Text": "表扬！\n真机伶不只在竞赛中表现优异，\n也在社群平台上宣扬、炒热了赛马娘界！",
            "ChoiceDataList": [],
            "ColorTextInfoList": []
        },
        {
            "Name": "秋川理事长",
            "Text": "因此将赠与你！“CC奖”！",
            "ChoiceDataList": [],
            "ColorTextInfoList": []
        },
        {
            "Name": "真机伶",
            "Text": "“CC奖”？这难道是……！",
            "ChoiceDataList": [],
            "ColorTextInfoList": []
        },
        {
            "Name": "秋川理事长",
            "Text": "──公布！就是\n“Crown of Cuteness”奖！",
            "ChoiceDataList": [],
            "ColorTextInfoList": []
        },
        {
            "Name": "真机伶",
            "Text": "……！\n可爱的王冠……！",
            "ChoiceDataList": [],
            "ColorTextInfoList": []
        },
        {
            "Name": "真机伶",
            "Text": "真机伶好开心哦。\n谢谢♪",
            "ChoiceDataList": [],
            "ColorTextInfoList": []
        },
        {
            "Name": "真机伶",
            "Text": "哥哥～！\n真机伶成功了──！",
            "ChoiceDataList": [
                "！？"
            ],
            "ColorTextInfoList": []
        },
        {
            "Name": "真机伶",
            "Text": "姐姐～！\n真机伶成功了──！",
            "ChoiceDataList": [
                "！？"
            ],
            "ColorTextInfoList": []
        },
        {
            "Name": "主持人",
            "Text": "哥哥？你的家人也有来到现场吗？",
            "ChoiceDataList": [],
            "ColorTextInfoList": []
        },
        {
            "Name": "主持人",
            "Text": "姐姐？你的家人也有来到现场吗？",
            "ChoiceDataList": [],
            "ColorTextInfoList": []
        },
        {
            "Name": "真机伶",
            "Text": "嗯──我们和家人一样，\n有着非常深～厚的关系♪",
            "ChoiceDataList": [
                "！？！？"
            ],
            "ColorTextInfoList": []
        },
        {
            "Name": "真机伶",
            "Text": "耶嘿♪",
            "ChoiceDataList": [],
            "ColorTextInfoList": []
        },
        {
            "Name": "独白",
            "Text": "虽然被她吓了一跳……\n但真机伶就此成为了\n名符其实最受喜爱的赛马娘！",
            "ChoiceDataList": [],
            "ColorTextInfoList": []
        },
        {
            "Name": "独白",
            "Text": "然后……",
            "ChoiceDataList": [],
            "ColorTextInfoList": []
        },
        {
            "Name": "记者",
            "Text": "──那最后再问一个问题。\n因为这次你获颁了一项特别奖……",
            "ChoiceDataList": [],
            "ColorTextInfoList": []
        },
        {
            "Name": "记者",
            "Text": "想请问真机伶今后的目标是什么？",
            "ChoiceDataList": [],
            "ColorTextInfoList": []
        },
        {
            "Name": "真机伶",
            "Text": "目标当然已经决定好了哦♪",
            "ChoiceDataList": [],
            "ColorTextInfoList": []
        },
        {
            "Name": "真机伶",
            "Text": "这次获得这个奖项，\n也算是代表我该做的事情告一段落了吧。\n所以接下来……",
            "ChoiceDataList": [],
            "ColorTextInfoList": []
        },
        {
            "Name": "真机伶",
            "Text": "我想要试着迈向国际！",
            "ChoiceDataList": [
                "……！"
            ],
            "ColorTextInfoList": []
        },
        {
            "Name": "真机伶",
            "Text": "我要去见见\n今后能亲眼见到真机伶的幸运儿们。",
            "ChoiceDataList": [],
            "ColorTextInfoList": []
        },
        {
            "Name": "真机伶",
            "Text": "真机伶为了传递可爱的理念，\n会继续前往各地的♪",
            "ChoiceDataList": [],
            "ColorTextInfoList": []
        },
        {
            "Name": "真机伶",
            "Text": "大家就好好期待和真机伶一起\n拓展可爱的循环吧～！",
            "ChoiceDataList": [],
            "ColorTextInfoList": []
        },
        {
            "Name": "独白",
            "Text": "──这个采访播出后，\n当天国际流行趋势\n都围绕在“Curren”上，结果……",
            "ChoiceDataList": [],
            "ColorTextInfoList": []
        },
        {
            "Name": "真机伶",
            "Text": "哥哥，登机报到手续办好咯！",
            "ChoiceDataList": [
                "……咦！？"
            ],
            "ColorTextInfoList": []
        },
        {
            "Name": "真机伶",
            "Text": "姐姐，登机报到手续办好咯！",
            "ChoiceDataList": [
                "……咦！？"
            ],
            "ColorTextInfoList": []
        },
        {
            "Name": "独白",
            "Text": "当我回过神时，\n我们已经在机场并准备要飞向世界了……！",
            "ChoiceDataList": [],
            "ColorTextInfoList": []
        },
        {
            "Name": "真机伶",
            "Text": "嗯？怎么好像在恍神啊？\n真是的～打起精神来呀！",
            "ChoiceDataList": [],
            "ColorTextInfoList": []
        },
        {
            "Name": "真机伶",
            "Text": "今天是我们要踏上新的可爱旅程的日子耶？",
            "ChoiceDataList": [],
            "ColorTextInfoList": []
        },
        {
            "Name": "真机伶",
            "Text": "可爱之后还有超可爱，\n超可爱之后还有究极可爱……",
            "ChoiceDataList": [],
            "ColorTextInfoList": []
        },
        {
            "Name": "真机伶",
            "Text": "要继续追逐这个无止境的梦想才行啊♪",
            "ChoiceDataList": [],
            "ColorTextInfoList": []
        },
        {
            "Name": "真机伶",
            "Text": "真机伶非常确信。",
            "ChoiceDataList": [],
            "ColorTextInfoList": []
        },
        {
            "Name": "真机伶",
            "Text": "只要有哥哥在我身边……\n就可以无限散播可爱的理念。",
            "ChoiceDataList": [],
            "ColorTextInfoList": []
        },
        {
            "Name": "真机伶",
            "Text": "只要有姐姐在我身边……\n就可以无限散播可爱的理念。",
            "ChoiceDataList": [],
            "ColorTextInfoList": []
        },
        {
            "Name": "真机伶",
            "Text": "而．且．啊！",
            "ChoiceDataList": [],
            "ColorTextInfoList": []
        },
        {
            "Name": "真机伶",
            "Text": "只要有哥哥在身边，\n真机伶就会是宇宙第一可爱的哦？",
            "ChoiceDataList": [
                "！！"
            ],
            "ColorTextInfoList": []
        },
        {
            "Name": "真机伶",
            "Text": "只要有姐姐在身边，\n真机伶就会是宇宙第一可爱的哦？",
            "ChoiceDataList": [
                "！！"
            ],
            "ColorTextInfoList": []
        },
        {
            "Name": "真机伶",
            "Text": "所以啊，哥哥，\n今后也要继续一～直只看着真机伶哦♪",
            "ChoiceDataList": [],
            "ColorTextInfoList": []
        },
        {
            "Name": "真机伶",
            "Text": "所以啊，姐姐，\n今后也要继续一～直只看着真机伶哦♪",
            "ChoiceDataList": [],
            "ColorTextInfoList": []
        }
    ]
}