{
    "Title": "有马纪念结束后．神级领头接力MAX☆",
    "TextBlockList": [
        {
            "Name": "",
            "Text": "",
            "ChoiceDataList": [],
            "ColorTextInfoList": []
        },
        {
            "Name": "",
            "Text": "“上吧──！好麻吉──！！”\n接收到一起领头的大拓太阳神\n来自背后的声援，目白善信再次加速。",
            "ChoiceDataList": [],
            "ColorTextInfoList": []
        },
        {
            "Name": "",
            "Text": "──她称霸了“有马纪念”。\n呼喊“善、信！”的声音响遍会场。",
            "ChoiceDataList": [],
            "ColorTextInfoList": []
        },
        {
            "Name": "",
            "Text": "“目白的异端”目白善信。这位威风凛凛的\n逃亡者，将其名烙印在人们的记忆中──",
            "ChoiceDataList": [],
            "ColorTextInfoList": []
        },
        {
            "Name": "",
            "Text": "在胜利者访谈中，\n她做出了最大最强的派对玩咖行为，\n然后就爆速逃脱了。",
            "ChoiceDataList": [],
            "ColorTextInfoList": []
        }
    ]
}