{
    "Title": "下次不会输了！",
    "TextBlockList": [
        {
            "Name": "",
            "Text": "",
            "ChoiceDataList": [],
            "ColorTextInfoList": []
        },
        {
            "Name": "醒目飞鹰",
            "Text": "我……又输了。\n我又没能站上C位……",
            "ChoiceDataList": [],
            "ColorTextInfoList": []
        },
        {
            "Name": "醒目飞鹰",
            "Text": "──好不甘心！！",
            "ChoiceDataList": [],
            "ColorTextInfoList": []
        },
        {
            "Name": "醒目飞鹰",
            "Text": "飞鹰子……不想再这么下去！\n为了获胜，我要更加更加努力地训练！",
            "ChoiceDataList": [],
            "ColorTextInfoList": []
        },
        {
            "Name": "醒目飞鹰",
            "Text": "我一定要成为带给大家梦想与希望的──\n顶尖赛马娘偶像！！",
            "ChoiceDataList": [
                "太过焦急不是件好事哦",
                "太过焦急不是件好事哦",
                "嗯！展现你的赛马娘偶像精神吧！",
                "嗯！展现你的赛马娘偶像精神吧！"
            ],
            "ColorTextInfoList": []
        },
        {
            "Name": "醒目飞鹰",
            "Text": "我一定要成为带给大家梦想与希望的──\n顶尖赛马娘偶像！！",
            "ChoiceDataList": [
                "太过焦急不是件好事哦",
                "太过焦急不是件好事哦",
                "嗯！展现你的赛马娘偶像精神吧！",
                "嗯！展现你的赛马娘偶像精神吧！"
            ],
            "ColorTextInfoList": []
        },
        {
            "Name": "醒目飞鹰",
            "Text": "可是……！连续输了好几次，\n不管怎样都会焦急啊……！",
            "ChoiceDataList": [],
            "ColorTextInfoList": []
        },
        {
            "Name": "醒目飞鹰",
            "Text": "飞鹰子现在就想获得可以跑赢的实力！\n得变更成斯巴达式赛马娘偶像路线才行！",
            "ChoiceDataList": [
                "变更偶像路线时得谨慎考虑才行"
            ],
            "ColorTextInfoList": []
        },
        {
            "Name": "醒目飞鹰",
            "Text": "──啊！！\n说、说得也是……！！",
            "ChoiceDataList": [],
            "ColorTextInfoList": []
        },
        {
            "Name": "醒目飞鹰",
            "Text": "要是自己最喜欢的偶像突然改变气质，\n大家应该……会吓一跳吧。",
            "ChoiceDataList": [],
            "ColorTextInfoList": []
        },
        {
            "Name": "醒目飞鹰",
            "Text": "飞鹰子也不想看到那种事发生。\n赛马娘偶像必须重视粉丝的心情……！",
            "ChoiceDataList": [
                "以你现在的样子继续努力就行了",
                "以你现在的样子继续努力就行了"
            ],
            "ColorTextInfoList": []
        },
        {
            "Name": "醒目飞鹰",
            "Text": "……嗯！\n谢谢你，训练员！",
            "ChoiceDataList": [],
            "ColorTextInfoList": []
        },
        {
            "Name": "醒目飞鹰",
            "Text": "飞鹰子会和之前一样……\n继续努力成为可爱的顶尖赛马娘偶像！",
            "ChoiceDataList": [],
            "ColorTextInfoList": []
        },
        {
            "Name": "醒目飞鹰",
            "Text": "……当然没问题！！",
            "ChoiceDataList": [],
            "ColorTextInfoList": []
        },
        {
            "Name": "醒目飞鹰",
            "Text": "飞鹰子会拼上赛马娘偶像精神的全力，\n拼命地加油的……",
            "ChoiceDataList": [],
            "ColorTextInfoList": []
        },
        {
            "Name": "醒目飞鹰",
            "Text": "所以希望训练员也能拼命地\n为飞鹰子加油打气……！",
            "ChoiceDataList": [
                "加油！加油！飞鹰子～！！"
            ],
            "ColorTextInfoList": []
        },
        {
            "Name": "醒目飞鹰",
            "Text": "……嘿嘿。\n多亏了你，我获得活力咯！",
            "ChoiceDataList": [],
            "ColorTextInfoList": []
        },
        {
            "Name": "醒目飞鹰",
            "Text": "飞鹰子……下次不会再输了！\n我要取得胜利，把最棒的舞台呈现给大家☆",
            "ChoiceDataList": [],
            "ColorTextInfoList": []
        }
    ]
}