{
    "Title": "每天都无比美丽☆★",
    "TextBlockList": [
        {
            "Name": "",
            "Text": "",
            "ChoiceDataList": [],
            "ColorTextInfoList": []
        },
        {
            "Name": "美丽周日",
            "Text": "嗯～！热腾腾的米饭～♪\n非～常非常美丽★",
            "ChoiceDataList": [],
            "ColorTextInfoList": []
        },
        {
            "Name": "美丽周日",
            "Text": "奇怪～？不过为什么\n热腾腾的米饭看起来糊糊的呢？",
            "ChoiceDataList": [],
            "ColorTextInfoList": []
        },
        {
            "Name": "重炮",
            "Text": "人家知道为什么！\n一定是因为散发着水蒸气的关系～！",
            "ChoiceDataList": [],
            "ColorTextInfoList": []
        },
        {
            "Name": "美丽周日",
            "Text": "啊哈哈哈☆原来是水蒸气啊～！\n那还真是美丽呢★",
            "ChoiceDataList": [],
            "ColorTextInfoList": []
        },
        {
            "Name": "两人",
            "Text": "糊糊的～糊糊的～水蒸气～☆",
            "ChoiceDataList": [],
            "ColorTextInfoList": []
        },
        {
            "Name": "两人",
            "Text": "啊哈哈哈哈哈～！",
            "ChoiceDataList": [],
            "ColorTextInfoList": []
        },
        {
            "Name": "美丽周日",
            "Text": "啊！那是银柳耶☆\n银柳的毛究竟是毛球还是叶子呢！？",
            "ChoiceDataList": [],
            "ColorTextInfoList": []
        },
        {
            "Name": "重炮",
            "Text": "人家知道！\n那一定是长得像毛球的叶子啦♪",
            "ChoiceDataList": [],
            "ColorTextInfoList": []
        },
        {
            "Name": "美丽周日",
            "Text": "啊哈哈哈☆真的耶看起来好像毛球～！\n非～常非常美丽★",
            "ChoiceDataList": [],
            "ColorTextInfoList": []
        },
        {
            "Name": "两人",
            "Text": "毛毛的～毛毛的～银柳～☆",
            "ChoiceDataList": [],
            "ColorTextInfoList": []
        },
        {
            "Name": "两人",
            "Text": "啊哈哈哈哈哈～！",
            "ChoiceDataList": [],
            "ColorTextInfoList": []
        },
        {
            "Name": "美丽周日",
            "Text": "哇啊～！好多社会人士☆\n不过为什么大家都急急忙忙的呢？",
            "ChoiceDataList": [],
            "ColorTextInfoList": []
        },
        {
            "Name": "重炮",
            "Text": "人家知道为什么！\n一定是因为大家很努力工作喔♪",
            "ChoiceDataList": [],
            "ColorTextInfoList": []
        },
        {
            "Name": "美丽周日",
            "Text": "这样啊～！？那真是太伟大了！\n非～常非常美丽☆",
            "ChoiceDataList": [],
            "ColorTextInfoList": []
        },
        {
            "Name": "两人",
            "Text": "谢谢你们～总是这么～努力☆",
            "ChoiceDataList": [],
            "ColorTextInfoList": []
        },
        {
            "Name": "两人",
            "Text": "今天也要加油喔，但别太勉强喔～♪",
            "ChoiceDataList": [],
            "ColorTextInfoList": []
        },
        {
            "Name": "美丽周日",
            "Text": "我回来了～！这里是\n我们每天奔跑生活的特雷森学园☆",
            "ChoiceDataList": [],
            "ColorTextInfoList": []
        },
        {
            "Name": "美丽周日",
            "Text": "话说回来，为什么赛马娘要跑步呢？\n有什么特殊的原因吗～？",
            "ChoiceDataList": [],
            "ColorTextInfoList": []
        },
        {
            "Name": "重炮",
            "Text": "那是因为，嗯～",
            "ChoiceDataList": [],
            "ColorTextInfoList": []
        },
        {
            "Name": "重炮",
            "Text": "──啊！人家知道为什么！\n因为跑步没有终点！",
            "ChoiceDataList": [],
            "ColorTextInfoList": []
        },
        {
            "Name": "美丽周日",
            "Text": "没有终点～！？\n这样啊，因为地球是圆的嘛！",
            "ChoiceDataList": [],
            "ColorTextInfoList": []
        },
        {
            "Name": "美丽周日",
            "Text": "这个世界有无限的美丽☆\n无论走到哪都是一个圈★",
            "ChoiceDataList": [],
            "ColorTextInfoList": []
        },
        {
            "Name": "两人",
            "Text": "绕圈圈～绕圈圈到地球的尽头☆\n无论今天明天都在绕圈圈～☆",
            "ChoiceDataList": [],
            "ColorTextInfoList": []
        },
        {
            "Name": "两人",
            "Text": "啊哈哈哈！啊哈哈哈哈哈～！",
            "ChoiceDataList": [],
            "ColorTextInfoList": []
        },
        {
            "Name": "采珠",
            "Text": "那两个孩子终于到达那个境地了呢……\n──到达世界的深渊。",
            "ChoiceDataList": [],
            "ColorTextInfoList": []
        },
        {
            "Name": "丸善斯基",
            "Text": "呵呵，毕竟那个年纪的孩子\n可是所向无敌的嘛♪",
            "ChoiceDataList": [],
            "ColorTextInfoList": []
        }
    ]
}